pyridoxine/__init__.py
pyridoxine/athena/__init__.py
pyridoxine/athena/hst.py
pyridoxine/plt/__init__.py
pyridoxine/plt/defaults.py
pyridoxine/utility/__init__.py
pyridoxine/utility/constants.py
pyridoxine/utility/rw.py
pyridoxine/utility/vec.py
pyridoxine-0.4.0.dist-info/LICENSE.txt
pyridoxine-0.4.0.dist-info/METADATA
pyridoxine-0.4.0.dist-info/WHEEL
pyridoxine-0.4.0.dist-info/top_level.txt
pyridoxine-0.4.0.dist-info/RECORD
